visonicalarmlocal/__init__.py
visonicalarmlocal/api.py
visonicalarmlocal/devices.py
visonicalarmlocal/exceptions.py
visonicalarmlocal-0.0.2.dist-info/LICENSE
visonicalarmlocal-0.0.2.dist-info/METADATA
visonicalarmlocal-0.0.2.dist-info/WHEEL
visonicalarmlocal-0.0.2.dist-info/top_level.txt
visonicalarmlocal-0.0.2.dist-info/RECORD
