Metadata-Version: 2.1
Name: visonicalarmlocal
Version: 0.0.2
Summary: A simple library for the Visonic Alarm Local API written in Python 3.
Home-page: https://github.com/dartoisr/visonicalarmlocal
Author: Rémi Dartois
Author-email: remi@dartoisr.fr
Classifier: Programming Language :: Python :: 3
Classifier: License :: OSI Approved :: MIT License
Classifier: Operating System :: OS Independent
Requires-Python: >=3.6
License-File: LICENSE
Requires-Dist: requests
